c3DataMigration/__init__.py
c3DataMigration/c3DataTransfer.py
c3DataMigration/c3Helpers/__init__.py
c3DataMigration/c3Helpers/c3BatchJobs.py
c3DataMigration/c3Helpers/c3FileSystem.py
c3DataMigration/c3Helpers/c3PythonClasses.py
c3DataMigration/c3Helpers/c3Queues.py
c3DataMigration/c3Helpers/c3Request.py
c3DataMigration/c3Helpers/c3UsageStats.py
c3DataMigration/c3Helpers/c3UtilityMethods.py
c3DataMigration/c3MigrationMethods/__init__.py
c3DataMigration/c3MigrationMethods/c3DataDownload.py
c3DataMigration/c3MigrationMethods/c3DataRefreshCalcFields.py
c3DataMigration/c3MigrationMethods/c3DataRemove.py
c3DataMigration/c3MigrationMethods/c3DataUpload.py
c3_data_transfer_tool_jackdedobb-1.0.96.dist-info/LICENSE
c3_data_transfer_tool_jackdedobb-1.0.96.dist-info/METADATA
c3_data_transfer_tool_jackdedobb-1.0.96.dist-info/WHEEL
c3_data_transfer_tool_jackdedobb-1.0.96.dist-info/top_level.txt
c3_data_transfer_tool_jackdedobb-1.0.96.dist-info/RECORD
