Metadata-Version: 2.1
Name: c3-data-transfer-tool-jackdedobb
Version: 1.0.96
Summary: Tool to help extracting and uploading data to C3 environments.
Home-page: https://github.com/c3-e/c3open/tools/jack-transfer-tool
Author: Jackson DeDobbelaere
Author-email: jackson.dedobbelaere@c3.ai
Classifier: Programming Language :: Python :: 3
Classifier: License :: OSI Approved :: GNU General Public License v3 (GPLv3)
Classifier: Operating System :: OS Independent
Requires-Python: >=3.6
License-File: LICENSE
Requires-Dist: progress
Requires-Dist: pytz
Requires-Dist: reprint
Requires-Dist: requests
